CHANGES.txt
LICENSE.txt
README.txt
bootstrap.py
setup.py
src/z3c/__init__.py
src/z3c.searcher.egg-info/PKG-INFO
src/z3c.searcher.egg-info/SOURCES.txt
src/z3c.searcher.egg-info/dependency_links.txt
src/z3c.searcher.egg-info/namespace_packages.txt
src/z3c.searcher.egg-info/not-zip-safe
src/z3c.searcher.egg-info/requires.txt
src/z3c.searcher.egg-info/top_level.txt
src/z3c/searcher/README.txt
src/z3c/searcher/__init__.py
src/z3c/searcher/browser.zcml
src/z3c/searcher/configure.zcml
src/z3c/searcher/criterium.pt
src/z3c/searcher/criterium.py
src/z3c/searcher/filter.pt
src/z3c/searcher/filter.py
src/z3c/searcher/form.py
src/z3c/searcher/interfaces.py
src/z3c/searcher/search.pt
src/z3c/searcher/session.py
src/z3c/searcher/table.pt
src/z3c/searcher/table.py
src/z3c/searcher/testing.py
src/z3c/searcher/tests.py
src/z3c/searcher/generations/__init__.py
src/z3c/searcher/generations/configure.zcml